source_amplitude/__init__.py
source_amplitude/components.py
source_amplitude/manifest.yaml
source_amplitude/run.py
source_amplitude/schemas/events.json
source_amplitude/source.py
source_amplitude/spec.yaml
source_amplitude/streams.py
airbyte_source_amplitude-0.6.19.dist-info/METADATA
airbyte_source_amplitude-0.6.19.dist-info/WHEEL
airbyte_source_amplitude-0.6.19.dist-info/entry_points.txt
airbyte_source_amplitude-0.6.19.dist-info/RECORD
