Metadata-Version: 2.3
Name: airbyte-source-amplitude
Version: 0.6.19
Summary: Source implementation for Amplitude.
License: MIT
Author: Airbyte
Author-email: contact@airbyte.io
Requires-Python: >=3.10,<3.12
Classifier: License :: OSI Approved :: MIT License
Classifier: Programming Language :: Python :: 3
Classifier: Programming Language :: Python :: 3.10
Classifier: Programming Language :: Python :: 3.11
Requires-Dist: airbyte-cdk (>=4,<5)
Project-URL: Documentation, https://docs.airbyte.com/integrations/sources/amplitude
Project-URL: Homepage, https://airbyte.com
Project-URL: Repository, https://github.com/airbytehq/airbyte
